com/__init__.py
com/vmware/__init__.py
com/vmware/cis_client.py
com/vmware/vapi_client.py
com/vmware/cis/__init__.py
com/vmware/cis/task_client.py
com/vmware/vapi/__init__.py
com/vmware/vapi/metadata_client.py
com/vmware/vapi/std_client.py
com/vmware/vapi/metadata/__init__.py
com/vmware/vapi/metadata/authentication_client.py
com/vmware/vapi/metadata/cli_client.py
com/vmware/vapi/metadata/metamodel_client.py
com/vmware/vapi/metadata/privilege_client.py
com/vmware/vapi/metadata/routing_client.py
com/vmware/vapi/metadata/authentication/__init__.py
com/vmware/vapi/metadata/authentication/service_client.py
com/vmware/vapi/metadata/metamodel/__init__.py
com/vmware/vapi/metadata/metamodel/resource_client.py
com/vmware/vapi/metadata/metamodel/service_client.py
com/vmware/vapi/metadata/privilege/__init__.py
com/vmware/vapi/metadata/privilege/service_client.py
com/vmware/vapi/metadata/routing/__init__.py
com/vmware/vapi/metadata/routing/service_client.py
com/vmware/vapi/std/__init__.py
com/vmware/vapi/std/activation_client.py
com/vmware/vapi/std/errors_client.py
com/vmware/vapi/std/interposition_client.py
com/vmware/vapi/std/introspection_client.py
dcli-3.0.0.dist-info/DESCRIPTION.rst
dcli-3.0.0.dist-info/METADATA
dcli-3.0.0.dist-info/RECORD
dcli-3.0.0.dist-info/WHEEL
dcli-3.0.0.dist-info/entry_points.txt
dcli-3.0.0.dist-info/metadata.json
dcli-3.0.0.dist-info/top_level.txt
vmware/__init__.py
vmware/vapi/__init__.py
vmware/vapi/core.py
vmware/vapi/exception.py
vmware/vapi/message.py
vmware/vapi/wsgi.py
vmware/vapi/bindings/__init__.py
vmware/vapi/bindings/common.py
vmware/vapi/bindings/converter.py
vmware/vapi/bindings/datetime_helper.py
vmware/vapi/bindings/enum.py
vmware/vapi/bindings/error.py
vmware/vapi/bindings/http_helper.py
vmware/vapi/bindings/message.py
vmware/vapi/bindings/skeleton.py
vmware/vapi/bindings/struct.py
vmware/vapi/bindings/stub.py
vmware/vapi/bindings/task_helper.py
vmware/vapi/bindings/type.py
vmware/vapi/bindings/uri_helper.py
vmware/vapi/client/__init__.py
vmware/vapi/client/dcli/__init__.py
vmware/vapi/client/dcli/__version__.py
vmware/vapi/client/dcli/cli.py
vmware/vapi/client/dcli/command.py
