Metadata-Version: 2.0
Name: dcli
Version: 3.0.0
Summary: Simplified command-line interface that you can use to automate tasks in your VMware Cloud on AWS and vCenter Server environments.
Home-page: http://vmware.com/go/dcli
Author: VMware
Author-email: vdaskalov@vmware.com
License: UNKNOWN
Platform: UNKNOWN
Classifier: Development Status :: 5 - Production/Stable
Classifier: Environment :: Console
Classifier: Intended Audience :: Developers
Classifier: Intended Audience :: Information Technology
Classifier: Intended Audience :: System Administrators
Classifier: Topic :: Utilities
Classifier: License :: OSI Approved :: MIT License
Classifier: Operating System :: MacOS
Classifier: Operating System :: Microsoft :: Windows
Classifier: Operating System :: POSIX
Classifier: Operating System :: Unix
Classifier: Programming Language :: Python
Classifier: Programming Language :: Python :: 2
Classifier: Programming Language :: Python :: 2.7
Classifier: Programming Language :: Python :: 3
Classifier: Programming Language :: Python :: 3.5
Classifier: Programming Language :: Python :: 3.6
Requires-Python: >=2.7
Requires-Dist: CacheControl (==0.12.3)
Requires-Dist: Pygments (>=2.3.1)
Requires-Dist: jmespath
Requires-Dist: lockfile (>=0.12.2)
Requires-Dist: lxml (>=3.4.1)
Requires-Dist: prompt-toolkit (<3.0.0,>=2.0.0)
Requires-Dist: pyOpenSSL (>=18.0.0)
Requires-Dist: requests (>=2.6.0)
Requires-Dist: service-identity (>=16.0.0)
Requires-Dist: setuptools
Requires-Dist: simplejson (>=3.6.5)
Requires-Dist: six (>=1.9)
Requires-Dist: wcwidth (>=0.1.6)
Requires-Dist: werkzeug (>=0.10.4)
